remdups/__init__.py
remdups/__main__.py
remdups/remdups.py
remdups-1.3.1.dist-info/DESCRIPTION.rst
remdups-1.3.1.dist-info/METADATA
remdups-1.3.1.dist-info/RECORD
remdups-1.3.1.dist-info/WHEEL
remdups-1.3.1.dist-info/entry_points.txt
remdups-1.3.1.dist-info/metadata.json
remdups-1.3.1.dist-info/top_level.txt
