Metadata-Version: 2.0
Name: remdups
Version: 1.3.1
Summary: remdups - remove duplicate files
Home-page: https://github.com/rpuntaie/remdups
Author: Roland Puntaier
Author-email: roland.puntaier@gmail.com
License: MIT
Keywords: Duplicate, File
Platform: UNKNOWN
Classifier: Development Status :: 5 - Production/Stable
Classifier: Environment :: Console
Classifier: License :: OSI Approved :: MIT License
Classifier: Natural Language :: English
Classifier: Operating System :: OS Independent
Classifier: Operating System :: POSIX
Classifier: Programming Language :: Python :: 3.6
Classifier: Intended Audience :: End Users/Desktop
Classifier: Intended Audience :: System Administrators
Classifier: Intended Audience :: Information Technology
Classifier: Topic :: Utilities
Classifier: Topic :: System :: Archiving
Classifier: Topic :: System :: Systems Administration
Requires-Dist: pillow
Provides-Extra: develop
Requires-Dist: pillow; extra == 'develop'
Requires-Dist: piexif; extra == 'develop'
Requires-Dist: pytest-toolbox; extra == 'develop'
Requires-Dist: pytest-coverage; extra == 'develop'
